[{"container-title":"Water Resources Research","author":[{"given":"Hoshin Vijai","family":"Gupta"},{"given":"Harald","family":"Kling"}],"DOI":"10.1029/2011wr010962","type":"article-journal","id":"Gupta_2011","citation-key":"Gupta_2011","ISSN":"1944-7973","issue":"10","issued":{"date-parts":[[2011,10]]},"publisher":"American Geophysical Union (AGU)","title":"On typical range, sensitivity, and normalization of Mean Squared Error and Nash‐Sutcliffe Efficiency type metrics","URL":"http://dx.doi.org/10.1029/2011WR010962","volume":"47","_graph":[{"type":"@biblatex/text","data":" @article{Gupta_2011, title={On typical range, sensitivity, and normalization of Mean Squared Error and Nash‐Sutcliffe Efficiency type metrics}, volume={47}, ISSN={1944-7973}, url={http://dx.doi.org/10.1029/2011WR010962}, DOI={10.1029/2011wr010962}, number={10}, journal={Water Resources Research}, publisher={American Geophysical Union (AGU)}, author={Gupta, Hoshin Vijai and Kling, Harald}, year={2011}, month=oct }\n"},{"type":"@biblatex/entries+list"},{"type":"@csl/list+object"}]}]